lazygit_rocker/__init__.py
lazygit_rocker/lazygit_rocker.py
lazygit_rocker/templates/lazygit_snippet.Dockerfile
lazygit_rocker-0.0.1.dist-info/METADATA
lazygit_rocker-0.0.1.dist-info/WHEEL
lazygit_rocker-0.0.1.dist-info/entry_points.txt
lazygit_rocker-0.0.1.dist-info/licenses/LICENSE
lazygit_rocker-0.0.1.dist-info/RECORD
